radarr_mcp_server/__init__.py
radarr_mcp_server/server.py
radarr_mcp-0.2.0.dist-info/METADATA
radarr_mcp-0.2.0.dist-info/WHEEL
radarr_mcp-0.2.0.dist-info/entry_points.txt
radarr_mcp-0.2.0.dist-info/RECORD
